django_fixedassets_ve-0.1.0.dist-info/licenses/LICENSE
fixedassets/__init__.py
fixedassets/apps.py
fixedassets/conf.py
fixedassets/enums.py
fixedassets/api/serializers.py
fixedassets/api/urls.py
fixedassets/api/views.py
fixedassets/mgmt/commands/fa_bootstrap_demo.py
fixedassets/models/asset.py
fixedassets/models/config.py
fixedassets/models/movement.py
fixedassets/models/schedule.py
fixedassets/posting/adapters.py
fixedassets/utils/depreciation.py
fixedassets/utils/money.py
django_fixedassets_ve-0.1.0.dist-info/METADATA
django_fixedassets_ve-0.1.0.dist-info/WHEEL
django_fixedassets_ve-0.1.0.dist-info/top_level.txt
django_fixedassets_ve-0.1.0.dist-info/RECORD
