Metadata-Version: 2.4
Name: django-fixedassets-ve
Version: 0.1.0
Summary: Fixed assets register with SLM/WDV depreciation, revaluation, disposal and accounting integration for Django.
Author-email: "Verified Enquiries / Tushar K." <support@verifiedenquiries.com>
License: MIT
Classifier: Framework :: Django
Classifier: Programming Language :: Python :: 3
Classifier: License :: OSI Approved :: MIT License
Requires-Python: >=3.11
License-File: LICENSE
Requires-Dist: Django>=5.0
Requires-Dist: djangorestframework>=3.15
Requires-Dist: django-finacc>=0.1.0
Dynamic: license-file
